pccs/__init__.py
pccs/__main__.py
pccs-0.2a3.dist-info/LICENSE
pccs-0.2a3.dist-info/METADATA
pccs-0.2a3.dist-info/WHEEL
pccs-0.2a3.dist-info/top_level.txt
pccs-0.2a3.dist-info/RECORD
