Metadata-Version: 2.1
Name: pccs
Version: 0.2a3
Summary: PCCS (Practical Color Coodinate System) package for Python
Home-page: https://bitbucket.org/emptypage/pccs-python/
Author: Masaaki Shibata
Author-email: mshibata@emptypage.jp
License: MIT
Keywords: color,color-science,colour,colour-science,pccs,munsell
Platform: UNKNOWN
Classifier: Programming Language :: Python :: 3
Classifier: Programming Language :: Python :: 3.9
Classifier: License :: OSI Approved :: MIT License
Classifier: Operating System :: OS Independent
License-File: LICENSE
Requires-Dist: colour-science
Requires-Dist: sympy
